jm_dep1/__init__.py
jm_dep1-0.3.dist-info/WHEEL
jm_dep1-0.3.dist-info/METADATA
jm_dep1-0.3.dist-info/RECORD
